json_txt/MainFiles.py
json_txt/SupportFuncs.py
json_txt/__init__.py
json_txt/compiler.py
json_txt-1.4.5.dist-info/METADATA
json_txt-1.4.5.dist-info/WHEEL
json_txt-1.4.5.dist-info/top_level.txt
json_txt-1.4.5.dist-info/RECORD
