Metadata-Version: 2.1
Name: json-txt
Version: 1.4.5
Summary: Make Your txt work like json
Home-page: https://github.com/kshitij1235/filemod
Author: kshitij jathar
Author-email: kshitijjathar7@gmail.com
License: MIT
Project-URL: Bug Tracker, https://github.com/kshitij1235/filemod/issues
Keywords: file
Platform: UNKNOWN
Classifier: Intended Audience :: Education
Classifier: Operating System :: Microsoft :: Windows :: Windows 10
Classifier: License :: OSI Approved :: MIT License
Classifier: Programming Language :: Python :: 3.5
Classifier: Programming Language :: Python :: 3.6
Classifier: Programming Language :: Python :: 3.7
Classifier: Programming Language :: Python :: 3.8
Requires-Dist: filemod
Requires-Dist: colored
